electoral_sim/__init__.py
electoral_sim/py.typed
electoral_sim/agents/__init__.py
electoral_sim/agents/party.py
electoral_sim/agents/party_strategy.py
electoral_sim/agents/voter.py
electoral_sim/analysis/__init__.py
electoral_sim/analysis/batch_runner.py
electoral_sim/analysis/duverger.py
electoral_sim/analysis/vse.py
electoral_sim/behavior/__init__.py
electoral_sim/behavior/voter_behavior.py
electoral_sim/core/__init__.py
electoral_sim/core/cli.py
electoral_sim/core/config.py
electoral_sim/core/constituency.py
electoral_sim/core/counting.py
electoral_sim/core/model.py
electoral_sim/core/voter_generation.py
electoral_sim/data/india_2024_sample.csv
electoral_sim/data/india_pc.py
electoral_sim/data/loaders.py
electoral_sim/dynamics/__init__.py
electoral_sim/dynamics/opinion_dynamics.py
electoral_sim/engine/__init__.py
electoral_sim/engine/coalition.py
electoral_sim/engine/government.py
electoral_sim/engine/gpu_accel.py
electoral_sim/engine/numba_accel.py
electoral_sim/events/__init__.py
electoral_sim/events/event_manager.py
electoral_sim/metrics/__init__.py
electoral_sim/metrics/indices.py
electoral_sim/presets/__init__.py
electoral_sim/presets/australia/__init__.py
electoral_sim/presets/australia/config.py
electoral_sim/presets/brazil/__init__.py
electoral_sim/presets/brazil/config.py
electoral_sim/presets/eu/__init__.py
electoral_sim/presets/eu/election.py
electoral_sim/presets/france/__init__.py
electoral_sim/presets/france/config.py
electoral_sim/presets/germany/__init__.py
electoral_sim/presets/germany/config.py
electoral_sim/presets/india/__init__.py
electoral_sim/presets/india/election.py
electoral_sim/presets/japan/__init__.py
electoral_sim/presets/japan/config.py
electoral_sim/presets/south_africa/__init__.py
electoral_sim/presets/south_africa/config.py
electoral_sim/presets/uk/__init__.py
electoral_sim/presets/uk/config.py
electoral_sim/presets/usa/__init__.py
electoral_sim/presets/usa/config.py
electoral_sim/systems/__init__.py
electoral_sim-0.1.0.dist-info/licenses/LICENSE
electoral_sim-0.1.0.dist-info/licenses/NOTICE
electoral_sim-0.1.0.dist-info/METADATA
electoral_sim-0.1.0.dist-info/WHEEL
electoral_sim-0.1.0.dist-info/entry_points.txt
electoral_sim-0.1.0.dist-info/top_level.txt
electoral_sim-0.1.0.dist-info/RECORD
