Metadata-Version: 2.4
Name: electoral-sim
Version: 0.1.0
Summary: High-performance agent-based electoral simulation toolkit with support for 11+ countries, multiple voting systems, and advanced voter behavior models
Author-email: Ayush <ayush12358@users.noreply.github.com>
Maintainer-email: Ayush <ayush12358@users.noreply.github.com>
License: Apache-2.0
Project-URL: Homepage, https://github.com/Ayush12358/ElectoralSim
Project-URL: Documentation, https://github.com/Ayush12358/ElectoralSim#readme
Project-URL: Repository, https://github.com/Ayush12358/ElectoralSim
Project-URL: Issues, https://github.com/Ayush12358/ElectoralSim/issues
Project-URL: Changelog, https://github.com/Ayush12358/ElectoralSim/releases
Keywords: election,simulation,agent-based-modeling,mesa,voting,electoral-systems,political-science,fptp,proportional-representation,coalition,opinion-dynamics,computational-social-science
Classifier: Development Status :: 4 - Beta
Classifier: Intended Audience :: Science/Research
Classifier: Intended Audience :: Education
Classifier: License :: OSI Approved :: Apache Software License
Classifier: Operating System :: OS Independent
Classifier: Programming Language :: Python :: 3
Classifier: Programming Language :: Python :: 3.12
Classifier: Programming Language :: Python :: 3.13
Classifier: Topic :: Scientific/Engineering
Classifier: Topic :: Scientific/Engineering :: Artificial Life
Classifier: Topic :: Scientific/Engineering :: Information Analysis
Classifier: Typing :: Typed
Requires-Python: >=3.12
License-File: LICENSE
License-File: NOTICE
Requires-Dist: mesa>=3.4.0
Requires-Dist: polars>=0.20.0
Requires-Dist: numpy<2.0.0,>=1.24.0
Requires-Dist: networkx>=3.0
Requires-Dist: numba>=0.60.1
Provides-Extra: viz
Requires-Dist: matplotlib>=3.7.0; extra == "viz"
Requires-Dist: plotly>=5.18.0; extra == "viz"
Requires-Dist: streamlit>=1.30.0; extra == "viz"
Provides-Extra: gpu
Requires-Dist: cupy-cuda12x>=12.0.0; extra == "gpu"
Provides-Extra: dev
Requires-Dist: pytest>=7.0.0; extra == "dev"
Requires-Dist: pytest-cov>=4.0.0; extra == "dev"
Requires-Dist: hypothesis>=6.0.0; extra == "dev"
Requires-Dist: black>=23.0.0; extra == "dev"
Requires-Dist: ruff>=0.1.0; extra == "dev"
Requires-Dist: mypy>=1.0.0; extra == "dev"
Requires-Dist: pre-commit>=3.0.0; extra == "dev"
Provides-Extra: docs
Requires-Dist: mkdocs>=1.5.0; extra == "docs"
Requires-Dist: mkdocs-material>=9.0.0; extra == "docs"
Requires-Dist: mkdocstrings[python]>=0.24.0; extra == "docs"
Provides-Extra: all
Requires-Dist: electoral-sim[dev,docs,viz]; extra == "all"
Dynamic: license-file
